Metadata-Version: 1.2
Name: BaseModel
Version: 20190604.1625
Summary: SqlAlchemy's spuer class
Home-page: https://github.com/billsteve
Author: billsteve
Author-email: billsteve@126.com
Maintainer: billsteve
Maintainer-email: billsteve@126.com
License: MIT License
Platform: all
Classifier: Programming Language :: Python :: 3.6
Classifier: Programming Language :: Python :: 3.7
Classifier: Topic :: Software Development :: Libraries
